tempenv/__init__.py
tempenv/py.typed
tempenv/tempenv.py
tempenv/version.py
tempenv-2.1.0.dist-info/LICENSE
tempenv-2.1.0.dist-info/METADATA
tempenv-2.1.0.dist-info/WHEEL
tempenv-2.1.0.dist-info/top_level.txt
tempenv-2.1.0.dist-info/RECORD
