Metadata-Version: 2.1
Name: tempenv
Version: 2.1.0
Summary: Environment Variable Context Manager
Home-page: https://github.com/jeking3/tempenv
Download-URL: https://github.com/jeking3/tempenv/archive/main.zip
Author: James E. King III
Author-email: jking@apache.org
License: Apache License 2.0
Keywords: temporary,environment variable,context manager,test,testing
Classifier: Development Status :: 5 - Production/Stable
Classifier: Intended Audience :: Developers
Classifier: License :: OSI Approved :: Apache Software License
Classifier: Natural Language :: English
Classifier: Operating System :: OS Independent
Classifier: Programming Language :: Python :: 3
Classifier: Programming Language :: Python :: 3.9
Classifier: Programming Language :: Python :: 3.10
Classifier: Programming Language :: Python :: 3.11
Classifier: Programming Language :: Python :: 3.12
Classifier: Programming Language :: Python :: 3.13
Classifier: Topic :: Security
Classifier: Topic :: System :: Shells
Classifier: Topic :: Utilities
Classifier: Typing :: Typed
Requires-Python: >=3.9
License-File: LICENSE
Provides-Extra: dev
Requires-Dist: pip-outdated~=0.7.0; extra == "dev"
Requires-Dist: pre-commit~=4.2.0; extra == "dev"
Requires-Dist: readme-renderer~=44.0; extra == "dev"
Requires-Dist: setuptools~=72.1; extra == "dev"
Requires-Dist: tox~=4.24.2; extra == "dev"
Requires-Dist: twine~=6.1.0; extra == "dev"
Requires-Dist: wheel~=0.45.1; extra == "dev"
Provides-Extra: test
Requires-Dist: coverage~=7.7.1; extra == "test"
Requires-Dist: pytest~=8.3.5; extra == "test"
